{
  "url": "https://www.sec.gov/Archives/edgar/data/1463101/000146310125000075/0001463101-25-000075.hdr.sgml",
  "status_code": 200,
  "headers": {
    "Content-Type": "text/sgml",
    "X-Frame-Options": "SAMEORIGIN",
    "x-amz-id-2": "bjOJL4MO2MzHIdqEX35kK6JGpVq7S/5pjdpS8S5WFQxqPi5U2X6uNaYIVxIEF10bf9N/KC9IKa0=",
    "x-amz-request-id": "DPZ6TH5T881Y03VV",
    "x-amz-replication-status": "COMPLETED",
    "Last-Modified": "Tue, 20 May 2025 20:12:42 GMT",
    "ETag": "\"5d2c352dfb63bb4cd523d6171a38e3e6-gzip\"",
    "x-amz-server-side-encryption": "AES256",
    "x-amz-meta-mode": "33188",
    "x-amz-version-id": "HzbEupnoJoJx2wfFd9UAMVn_80d7ztZp",
    "X-Content-Type-Options": "nosniff",
    "X-XSS-Protection": "1; mode=block",
    "Vary": "Accept-Encoding",
    "Date": "Mon, 06 Jul 2026 08:08:48 GMT",
    "Content-Length": "842",
    "Connection": "close",
    "Strict-Transport-Security": "max-age=31536000 ; includeSubDomains ; preload"
  },
  "content_length": 842,
  "sha256": "88d137a6e96d3e60489ff35dc847eb0a35922a6ec35bbcc341c8fab766a3347c",
  "saved_at_utc": "2026-07-06T08:08:48.529947+00:00"
}