{
  "url": "https://www.sec.gov/Archives/edgar/data/794367/000162828025010767/0001628280-25-010767.hdr.sgml",
  "status_code": 200,
  "headers": {
    "Content-Type": "text/sgml",
    "X-Frame-Options": "SAMEORIGIN",
    "x-amz-id-2": "1dJDTjo86A3FKRyt7tMZ9aZiv+UKPyuN5OwE3pY4gN1vDksx3OvWDYpo4PGTg0HA+/0MIV5DTah34b4BpvKUgT4VqAbp82qA",
    "x-amz-request-id": "CFPT3APVNFZ72VZ3",
    "x-amz-replication-status": "COMPLETED",
    "Last-Modified": "Thu, 06 Mar 2025 12:27:07 GMT",
    "ETag": "\"a8861e779cfc43aa618a5e82a98d0486-gzip\"",
    "x-amz-server-side-encryption": "AES256",
    "x-amz-meta-mode": "33188",
    "x-amz-version-id": "fBTuW42dvmF.1vDlwWHj1_stJUGDTXyR",
    "X-Content-Type-Options": "nosniff",
    "X-XSS-Protection": "1; mode=block",
    "Vary": "Accept-Encoding",
    "Date": "Thu, 09 Jul 2026 08:51:21 GMT",
    "Content-Length": "1139",
    "Connection": "close",
    "Strict-Transport-Security": "max-age=31536000 ; includeSubDomains ; preload"
  },
  "content_length": 1139,
  "sha256": "52d3d2ecfcd0fa13845ed55520325b633f47102e5ee7b1e128bce033b3780f17",
  "saved_at_utc": "2026-07-09T08:51:21.319661+00:00"
}