{
  "url": "https://www.sec.gov/Archives/edgar/data/92380/000119312525004026/0001193125-25-004026.hdr.sgml",
  "status_code": 200,
  "headers": {
    "Content-Type": "text/sgml",
    "X-Frame-Options": "SAMEORIGIN",
    "x-amz-id-2": "YJ5LyCvDnhE2nfcmajFmQ/BC+R+tqfrLZwWESbN0WOmKrKpdm35C6cCyUNcDRziAMWqXJNxKnpscKZ0beJqrmKQhsOEWiDa7",
    "x-amz-request-id": "P2JWW5FTMM93ZAGT",
    "x-amz-replication-status": "COMPLETED",
    "Last-Modified": "Fri, 10 Jan 2025 11:10:36 GMT",
    "ETag": "\"3f72dc1c877b3640342c21b06e178fa6-gzip\"",
    "x-amz-server-side-encryption": "AES256",
    "x-amz-meta-mode": "33188",
    "x-amz-version-id": "46lsc2wi1MpQ.oCMbCY3vEVstFJMBzG7",
    "X-Content-Type-Options": "nosniff",
    "X-XSS-Protection": "1; mode=block",
    "Vary": "Accept-Encoding",
    "Date": "Mon, 06 Jul 2026 08:07:34 GMT",
    "Content-Length": "961",
    "Connection": "close",
    "Strict-Transport-Security": "max-age=31536000 ; includeSubDomains ; preload"
  },
  "content_length": 961,
  "sha256": "0939db9f5dbf8a430bf61de2123558aa558d22a47c5a7e5160d680960b9038de",
  "saved_at_utc": "2026-07-06T08:07:34.820168+00:00"
}