{
  "url": "https://www.sec.gov/Archives/edgar/data/1048286/000162828025037592/mar-20250805.htm",
  "status_code": 200,
  "headers": {
    "Content-Type": "text/html",
    "X-Frame-Options": "SAMEORIGIN",
    "x-amz-id-2": "mh45LxVwBd/0Br+Hj7m04mws+rxf7mbfx7besrqRM4yq/XjQuoQ7alz+4Sevxfkur+vEfZIqiIGYa4/mOA7axK5IgAJp5Epx",
    "x-amz-request-id": "3T1Y4N4EKDBQTS5B",
    "x-amz-replication-status": "COMPLETED",
    "Last-Modified": "Tue, 05 Aug 2025 11:00:51 GMT",
    "x-amz-server-side-encryption": "AES256",
    "x-amz-meta-mode": "33188",
    "x-amz-version-id": "hb_f9HGxZesMSVcxKarVFvF74QQFt0qS",
    "X-Content-Type-Options": "nosniff",
    "X-XSS-Protection": "1; mode=block",
    "Vary": "Accept-Encoding",
    "Date": "Mon, 06 Jul 2026 07:25:38 GMT",
    "Content-Length": "35131",
    "Connection": "close",
    "Strict-Transport-Security": "max-age=31536000 ; includeSubDomains ; preload"
  },
  "content_length": 35131,
  "sha256": "8a305a1d91f7844d9b33127953592cb4a2df1f96ea849c17b3c977b310281be4",
  "saved_at_utc": "2026-07-06T07:25:39.056241+00:00"
}