{
  "url": "https://www.sec.gov/Archives/edgar/data/2041610/000114036126016758/0001140361-26-016758-index.html",
  "status_code": 200,
  "headers": {
    "Content-Type": "text/html",
    "X-Frame-Options": "SAMEORIGIN",
    "Last-Modified": "Fri, 24 Apr 2026 21:02:08 GMT",
    "X-Content-Type-Options": "nosniff",
    "X-XSS-Protection": "1; mode=block",
    "Vary": "Accept-Encoding",
    "Cache-Control": "no-cache",
    "Date": "Mon, 06 Jul 2026 07:25:00 GMT",
    "Content-Length": "13860",
    "Connection": "close",
    "Strict-Transport-Security": "max-age=31536000 ; includeSubDomains ; preload"
  },
  "content_length": 13860,
  "sha256": "0744509a24eeeff914dbe963dd3e519d5097f0a20d52b2612e9a64b37725ae50",
  "saved_at_utc": "2026-07-06T07:25:00.735105+00:00"
}