{
  "url": "https://www.sec.gov/Archives/edgar/data/2041610/000204161025000042/psky-20251110.htm",
  "status_code": 200,
  "headers": {
    "Content-Type": "text/html",
    "X-Frame-Options": "SAMEORIGIN",
    "x-amz-id-2": "PHZgmm8MY52tsqNnl6CcaDVLs4/1xfktJ35HPLb9TmKqK0Ox0x/M9BOkWXHK9l8pcipKGVL2mc0=",
    "x-amz-request-id": "XVD9Z4TGM7X4HXTP",
    "x-amz-replication-status": "COMPLETED",
    "Last-Modified": "Mon, 10 Nov 2025 21:03:46 GMT",
    "x-amz-server-side-encryption": "AES256",
    "x-amz-meta-mode": "33188",
    "x-amz-version-id": "pLCGGMdx4rBNXtn3b7NmZubfjxMQGA6I",
    "X-Content-Type-Options": "nosniff",
    "X-XSS-Protection": "1; mode=block",
    "Vary": "Accept-Encoding",
    "Date": "Mon, 06 Jul 2026 07:28:29 GMT",
    "Content-Length": "28672",
    "Connection": "close",
    "Strict-Transport-Security": "max-age=31536000 ; includeSubDomains ; preload"
  },
  "content_length": 28672,
  "sha256": "a39c957bebf524fc7efbd5f4f8fc13110424c7cb4ebb1a4b7dba1f7c2d8909fd",
  "saved_at_utc": "2026-07-06T07:28:29.178568+00:00"
}